__init__.py
soltan.py
Soltan-1.1.dist-info/LICENSE
Soltan-1.1.dist-info/METADATA
Soltan-1.1.dist-info/WHEEL
Soltan-1.1.dist-info/top_level.txt
Soltan-1.1.dist-info/RECORD
