Metadata-Version: 2.1
Name: Soltan
Version: 1.1
Summary: A module for Soltan Hashemi
Author-email: Mohammad Parsa Mortazavi <mpmms@outlook.com>
Classifier: Programming Language :: Python :: 3
Classifier: License :: OSI Approved :: MIT License
Classifier: Operating System :: OS Independent
Requires-Python: >=3.6
License-File: LICENSE
